general_navigation/__init__.py
general_navigation/__main__.py
general_navigation/base.py
general_navigation/carla_rl.py
general_navigation/carla_run.py
general_navigation/cli.py
general_navigation/common.py
general_navigation/mpc.py
general_navigation/settings.py
general_navigation/carla/__init__.py
general_navigation/carla/client.py
general_navigation/carla/helpers.py
general_navigation/carla/utils.py
general_navigation/diffusion_policy/__init__.py
general_navigation/diffusion_policy/codecs/__init__.py
general_navigation/diffusion_policy/codecs/imagecodecs_numcodecs.py
general_navigation/diffusion_policy/common/__init__.py
general_navigation/diffusion_policy/common/checkpoint_util.py
general_navigation/diffusion_policy/common/cv2_util.py
general_navigation/diffusion_policy/common/env_util.py
general_navigation/diffusion_policy/common/json_logger.py
general_navigation/diffusion_policy/common/nested_dict_util.py
general_navigation/diffusion_policy/common/normalize_util.py
general_navigation/diffusion_policy/common/pose_trajectory_interpolator.py
general_navigation/diffusion_policy/common/precise_sleep.py
general_navigation/diffusion_policy/common/pymunk_override.py
general_navigation/diffusion_policy/common/pymunk_util.py
general_navigation/diffusion_policy/common/pytorch_util.py
general_navigation/diffusion_policy/common/replay_buffer.py
general_navigation/diffusion_policy/common/robomimic_config_util.py
general_navigation/diffusion_policy/common/robomimic_util.py
general_navigation/diffusion_policy/common/sampler.py
general_navigation/diffusion_policy/common/timestamp_accumulator.py
general_navigation/diffusion_policy/config/__init__.py
general_navigation/diffusion_policy/config/train_bet_lowdim_workspace.yaml
general_navigation/diffusion_policy/config/train_diffusion_transformer_hybrid_workspace.yaml
general_navigation/diffusion_policy/config/train_diffusion_transformer_lowdim_kitchen_workspace.yaml
general_navigation-1.2.0.dist-info/LICENSE
general_navigation-1.2.0.dist-info/METADATA
general_navigation-1.2.0.dist-info/WHEEL
general_navigation-1.2.0.dist-info/entry_points.txt
general_navigation-1.2.0.dist-info/top_level.txt
general_navigation-1.2.0.dist-info/RECORD
