Metadata-Version: 2.1
Name: general_navigation
Version: 1.2.0
Summary: Awesome general_navigation created by AdityaNG
Home-page: https://github.com/AdityaNG/general-navigation/
Author: AdityaNG
License-File: LICENSE
Requires-Dist: torch >=2.2.2
Requires-Dist: torchvision >=0.17.2
Requires-Dist: numpy >=1.24.4
Requires-Dist: setuptools >=65.5.0
Requires-Dist: einops >=0.8.0
Requires-Dist: opencv-python >=4.9.0.80
Requires-Dist: efficientnet-pytorch ==0.7.1
Requires-Dist: vit-pytorch ==1.6.9
Requires-Dist: pygame ==2.5.2
Requires-Dist: platformdirs
Requires-Dist: gdown
Requires-Dist: diffusers
Requires-Dist: matplotlib
Requires-Dist: wandb
Requires-Dist: pydantic
Requires-Dist: simple-pid ==1.0.1
Requires-Dist: scipy ==1.10.0
Provides-Extra: test
Requires-Dist: pytest ; extra == 'test'
Requires-Dist: coverage ; extra == 'test'
Requires-Dist: flake8 ; extra == 'test'
Requires-Dist: black ; extra == 'test'
Requires-Dist: isort ; extra == 'test'
Requires-Dist: pytest-cov ; extra == 'test'
Requires-Dist: mypy ; extra == 'test'
Requires-Dist: gitchangelog ; extra == 'test'
Requires-Dist: mkdocs ; extra == 'test'
Requires-Dist: lark ; extra == 'test'
Requires-Dist: types-PyYAML ; extra == 'test'
